{
  "schema": [
    {
      "name": "label",
      "type": 7
    },
    {
      "name": "style",
      "type": 2
    },
    {
      "name": "name",
      "type": 7
    }
  ],
  "rows": [
    {
      "$id": 1,
      "label": "tlk44310186_02_msg0001",
      "style": 84,
      "name": "I know we got orders to let anyone\nand everyone enter the city, but...\nI just can't get used to it."
    },
    {
      "$id": 2,
      "label": "tlk44310186_02_msg0002",
      "style": 84,
      "name": "I can't help but be suspicious of\nall these unfamiliar faces."
    },
    {
      "$id": 3,
      "label": "tlk44310186_02_msg0003",
      "style": 84,
      "name": "How in the world do the other nations\nkeep public order...? I guess we'll have\nto learn, and soon..."
    }
  ]
}