{
  "schema": [
    {
      "name": "label",
      "type": 7
    },
    {
      "name": "style",
      "type": 2
    },
    {
      "name": "name",
      "type": 7
    }
  ],
  "rows": [
    {
      "$id": 1,
      "label": "qst201711_msg0001",
      "style": 84,
      "name": "Your Majesty! Are you unharmed?!"
    },
    {
      "$id": 2,
      "label": "qst201711_msg1001",
      "style": 84,
      "name": "Yes... I am fine. And all of you?"
    },
    {
      "$id": 3,
      "label": "qst201711_msg2001",
      "style": 84,
      "name": "We are fine, sir!\nEveryone is safe, sir!"
    },
    {
      "$id": 4,
      "label": "qst201711_msg2002",
      "style": 84,
      "name": "I see... That is good."
    },
    {
      "$id": 5,
      "label": "qst201711_msg0002",
      "style": 84,
      "name": "Still, to think that real\nvillains would infiltrate\na training exercise..."
    },
    {
      "$id": 6,
      "label": "qst201711_msg0003",
      "style": 84,
      "name": "This incident has brought\nseveral problems to light."
    },
    {
      "$id": 7,
      "label": "qst201711_msg0004",
      "style": 84,
      "name": "We must urgently review the\ndefense of the imperial capital."
    },
    {
      "$id": 8,
      "label": "qst201711_msg0005",
      "style": 84,
      "name": "Sir! I will also offer\nmy humble assistance!"
    },
    {
      "$id": 9,
      "label": "qst201711_msg0006",
      "style": 84,
      "name": "Thank you."
    },
    {
      "$id": 10,
      "label": "qst201711_msg0007",
      "style": 84,
      "name": "Your words are very reassuring."
    },
    {
      "$id": 11,
      "label": "qst201711_msg0008",
      "style": 84,
      "name": "No, no thanks are necessary, sir!"
    },
    {
      "$id": 12,
      "label": "qst201711_msg0009",
      "style": 84,
      "name": "I am merely doing my duty, sir!"
    },
    {
      "$id": 13,
      "label": "qst201711_msg0010",
      "style": 84,
      "name": "However, could I ask you to\nrefrain from such reckless\nbehavior in the future?"
    },
    {
      "$id": 14,
      "label": "qst201711_msg0011",
      "style": 84,
      "name": "...What do you mean by that, sir?"
    },
    {
      "$id": 15,
      "label": "qst201711_msg0012",
      "style": 84,
      "name": "Did I... do something\nto displease you, sir?"
    },
    {
      "$id": 16,
      "label": "qst201711_msg0013",
      "style": 84,
      "name": "No, that is not it."
    },
    {
      "$id": 17,
      "label": "qst201711_msg0014",
      "style": 84,
      "name": "It is just that if you\ncontinue to be so reckless\nand lose your life..."
    },
    {
      "$id": 18,
      "label": "qst201711_msg0015",
      "style": 84,
      "name": "I want you to remember that there\nare those who would grieve for you."
    },
    {
      "$id": 19,
      "label": "qst201711_msg0016",
      "style": 84,
      "name": "...Your Majesty..."
    },
    {
      "$id": 20,
      "label": "qst201711_msg0017",
      "style": 84,
      "name": "Please cherish your own\nlife as much as you do the\nlives of those you save."
    },
    {
      "$id": 21,
      "label": "qst201711_msg0018",
      "style": 84,
      "name": "Understood, sir!"
    },
    {
      "$id": 22,
      "label": "qst201711_msg0019",
      "style": 84,
      "name": "I, Newt, will carve Your\nMajesty's words into my heart..."
    },
    {
      "$id": 23,
      "label": "qst201711_msg0020",
      "style": 84,
      "name": "And pledge my further loyalty to\nHis Majesty the Emperor, sir!"
    },
    {
      "$id": 24,
      "label": "qst201711_msg0021",
      "style": 84,
      "name": "Uh, shouldn't you be pledging\nthat to your Driver?"
    },
    {
      "$id": 25,
      "label": "qst201711_msg0022",
      "style": 84,
      "name": "Um, shouldn't you be pledging\nthat to your Driver?"
    },
    {
      "$id": 26,
      "label": "qst201711_msg0023",
      "style": 84,
      "name": "Newt, as a Blade, you should be\npledging loyalty to your Driver."
    },
    {
      "$id": 27,
      "label": "qst201711_msg0024",
      "style": 84,
      "name": "Loyalty? Shouldn't ye be\npledgin' that to yer Driver?"
    },
    {
      "$id": 28,
      "label": "qst201711_msg0025",
      "style": 84,
      "name": "Huh? Um... Well, sir..."
    },
    {
      "$id": 29,
      "label": "qst201711_msg0026",
      "style": 84,
      "name": "Of course, I pledge loyalty to my Driver,\nsir, but I thought I should also pledge\nto His Majesty the Emperor..."
    },
    {
      "$id": 30,
      "label": "qst201711_msg0027",
      "style": 84,
      "name": "B-But it's not like one is higher\nor lower than the other, sir..."
    },
    {
      "$id": 31,
      "label": "qst201711_msg0028",
      "style": 84,
      "name": "Ah, um, well... I will serve them\nboth with all my heart, sir!"
    },
    {
      "$id": 32,
      "label": "qst201711_msg0029",
      "style": 84,
      "name": "Haha! What was that? That's so\nlike you, Newt, but so vague..."
    },
    {
      "$id": 33,
      "label": "qst201711_msg0030",
      "style": 84,
      "name": "Pfft! What was that? That's so\nlike you, Newt, but so vague..."
    },
    {
      "$id": 34,
      "label": "qst201711_msg0031",
      "style": 84,
      "name": "Hmph... I cannot accept\nsuch a vague answer."
    },
    {
      "$id": 35,
      "label": "qst201711_msg0032",
      "style": 84,
      "name": "Wahaha, what was that?\nYe're a vague one, Newt."
    },
    {
      "$id": 36,
      "label": "qst201711_msg0033",
      "style": 84,
      "name": "No, I did not mean to be vague\nor anything of the sort, sir..."
    },
    {
      "$id": 37,
      "label": "qst201711_msg0034",
      "style": 84,
      "name": "Fufufu..."
    },
    {
      "$id": 38,
      "label": "qst201711_msg0035",
      "style": 84,
      "name": "Ah, even His Majesty is laughing!\nThis is terrible, sirs!"
    }
  ]
}