{
  "schema": [
    {
      "name": "label",
      "type": 7
    },
    {
      "name": "style",
      "type": 2
    },
    {
      "name": "name",
      "type": 7
    }
  ],
  "rows": [
    {
      "$id": 1,
      "label": "qst201907_msg0001",
      "style": 84,
      "name": "Here, we found it."
    },
    {
      "$id": 2,
      "label": "qst201907_msg0002",
      "style": 84,
      "name": "Wow! It's beautiful... Thank you, miss!"
    },
    {
      "$id": 3,
      "label": "qst201907_msg0003",
      "style": 84,
      "name": "Ohhh... what an innocent\nand lovely smile."
    },
    {
      "$id": 4,
      "label": "qst201907_msg0004",
      "style": 84,
      "name": "My dear, would you be interested\nin joining our harem?"
    },
    {
      "$id": 5,
      "label": "qst201907_msg0005",
      "style": 84,
      "name": "She really has no boundaries..."
    },
    {
      "$id": 6,
      "label": "qst201907_msg0006",
      "style": 84,
      "name": "Hey, Rinne. Shouldn't we\nbe looking for the\nblack-feathered Nopon first?"
    },
    {
      "$id": 7,
      "label": "qst201907_msg0007",
      "style": 84,
      "name": "Oh, yes, that is right. We\nhad completely forgotten."
    },
    {
      "$id": 8,
      "label": "qst201907_msg0008",
      "style": 84,
      "name": "Let's ask this girl for more details."
    },
    {
      "$id": 9,
      "label": "qst201907_msg0009",
      "style": 84,
      "name": "You want to know about\nthe black Nopon, right?"
    },
    {
      "$id": 10,
      "label": "qst201907_msg0010",
      "style": 84,
      "name": "That is correct. Would you be so\nkind as to tell us in detail?"
    },
    {
      "$id": 11,
      "label": "qst201907_msg0011",
      "style": 84,
      "name": "Of course!"
    },
    {
      "$id": 12,
      "label": "qst201907_msg0012",
      "style": 84,
      "name": "When I bumped into the black\nNopon, he dropped a memo.\nWill this be useful?"
    },
    {
      "$id": 13,
      "label": "qst201907_msg0013",
      "style": 84,
      "name": "Ohhh! What a sweet child..."
    },
    {
      "$id": 14,
      "label": "qst201907_msg0014",
      "style": 84,
      "name": "This means we have no choice\nbut to add her to a special\nseat in our harem!"
    },
    {
      "$id": 15,
      "label": "qst201907_msg0015",
      "style": 84,
      "name": "Enough of that!"
    },
    {
      "$id": 16,
      "label": "qst201907_msg0016",
      "style": 84,
      "name": "More importantly, the memo's contents!"
    },
    {
      "$id": 17,
      "label": "qst201907_msg0017",
      "style": 84,
      "name": "...We know."
    },
    {
      "$id": 18,
      "label": "qst201907_msg0018",
      "style": 84,
      "name": "Ahem! Then we shall read!"
    },
    {
      "$id": 19,
      "label": "qst201907_msg0019",
      "style": 84,
      "name": "\"The secret meeting this time will be\nheld on the deck of the Uzushio. Be\nsure not to be late, mo.\" ...it says."
    },
    {
      "$id": 20,
      "label": "qst201907_msg0020",
      "style": 84,
      "name": "This is a memo for a secret meeting.\nNow we know exactly where he is!"
    },
    {
      "$id": 21,
      "label": "qst201907_msg0021",
      "style": 84,
      "name": "Indeed, it seems so."
    },
    {
      "$id": 22,
      "label": "qst201907_msg0022",
      "style": 84,
      "name": "Just you wait, black-feathered\nfool! We will bring down the\nhammer of justice upon you!"
    }
  ]
}