{
  "schema": [
    {
      "name": "label",
      "type": 7
    },
    {
      "name": "style",
      "type": 2
    },
    {
      "name": "name",
      "type": 7
    }
  ],
  "rows": [
    {
      "$id": 1,
      "label": "bf08520100_0010",
      "style": 82,
      "name": "Shin and the others?"
    },
    {
      "$id": 2,
      "label": "bf08520100_0020",
      "style": 82,
      "name": "They entered the World Tree."
    },
    {
      "$id": 3,
      "label": "bf08520100_0025",
      "style": 82,
      "name": "Now Metsu just needs to activate Aion."
    },
    {
      "$id": 4,
      "label": "bf08520100_0030",
      "style": 82,
      "name": "If we can hold this position and prevent them from advancing upward until then..."
    },
    {
      "$id": 5,
      "label": "bf08520100_0035",
      "style": 82,
      "name": "It's our victory."
    },
    {
      "$id": 6,
      "label": "bf08520100_0040",
      "style": 82,
      "name": "I see."
    },
    {
      "$id": 7,
      "label": "bf08520100_0042",
      "style": 82,
      "name": "Then we better give it our all."
    },
    {
      "$id": 8,
      "label": "bf08520100_0050",
      "style": 82,
      "name": "That light vortex...!"
    },
    {
      "$id": 9,
      "label": "bf08520100_0060",
      "style": 82,
      "name": "Your Holiness!\nOne of the amplifier towers has been..."
    },
    {
      "$id": 10,
      "label": "bf08520100_0070",
      "style": 82,
      "name": "Don't panic.\nThe area of effect has just narrowed slightly."
    },
    {
      "$id": 11,
      "label": "bf08520100_0080",
      "style": 82,
      "name": "They're already \"getting close.\""
    },
    {
      "$id": 12,
      "label": "bf08520100_0090",
      "style": 82,
      "name": "Concentrate the warrior monks to the front.\nKnock down those insects."
    }
  ]
}