{
  "schema": [
    {
      "name": "label",
      "type": 7
    },
    {
      "name": "style",
      "type": 2
    },
    {
      "name": "name",
      "type": 7
    }
  ],
  "rows": [
    {
      "$id": 1,
      "label": "campfev11_550_140_msg0001",
      "style": 84,
      "name": "Maybe if we wander around the capital,\nwe can get a handle on the problems\nand concerns of the people."
    },
    {
      "$id": 2,
      "label": "campfev11_550_140_msg0002",
      "style": 84,
      "name": "Good idea. Vox populi..."
    },
    {
      "$id": 3,
      "label": "campfev11_550_140_msg0003",
      "style": 84,
      "name": "Iira has much to celebrate.\nTechnology, wealth, and peace..."
    },
    {
      "$id": 4,
      "label": "campfev11_550_140_msg0004",
      "style": 84,
      "name": "But I'm sure that the people here\nare like any other, in having many\nproblems, small and large."
    },
    {
      "$id": 5,
      "label": "campfev11_550_140_msg0005",
      "style": 84,
      "name": "Yeah... The realities of life are more\nor less the same wherever you go.\nI wonder how helpful we can really be..."
    },
    {
      "$id": 6,
      "label": "campfev11_550_140_msg0006",
      "style": 84,
      "name": "Shin.. If people are in need, then we\nshould at least try to help them."
    },
    {
      "$id": 7,
      "label": "campfev11_550_140_msg0007",
      "style": 84,
      "name": "We still have time before Metsu gets\nhere. We should make good use of it."
    },
    {
      "$id": 8,
      "label": "campfev11_550_140_msg0008",
      "style": 84,
      "name": "Indeed."
    },
    {
      "$id": 9,
      "label": "campfev11_550_140_msg0009",
      "style": 84,
      "name": "Perhaps by aiding the community, we\nwill find allies in unexpected places."
    },
    {
      "$id": 10,
      "label": "campfev11_550_140_msg0010",
      "style": 84,
      "name": "There is surely merit in trying,\nis there not?"
    },
    {
      "$id": 11,
      "label": "campfev11_550_140_msg0011",
      "style": 84,
      "name": "Maybe you have a point..."
    }
  ]
}