{
  "schema": [
    {
      "name": "label",
      "type": 7
    },
    {
      "name": "style",
      "type": 2
    },
    {
      "name": "name",
      "type": 7
    }
  ],
  "rows": [
    {
      "$id": 1,
      "label": "kizunainn064_msg001",
      "style": 84,
      "name": "Hey, Seori."
    },
    {
      "$id": 2,
      "label": "kizunainn064_msg002",
      "style": 84,
      "name": "I heard there's a place\nwith nice scenery at a\nplace called Rita's Oasis."
    },
    {
      "$id": 3,
      "label": "kizunainn064_msg003",
      "style": 84,
      "name": "You want to go see it, right?"
    },
    {
      "$id": 4,
      "label": "kizunainn064_msg004",
      "style": 84,
      "name": "Eh? Not really to that extent, but[ML:Dash ]"
    },
    {
      "$id": 5,
      "label": "kizunainn064_msg005",
      "style": 84,
      "name": "Alriiiight! Let's get ready\nimmediately and go with everyone!"
    },
    {
      "$id": 6,
      "label": "kizunainn064_msg006",
      "style": 84,
      "name": "Onee-chan just wants to go herself[ML:Dash ]"
    }
  ]
}