{
  "schema": [
    {
      "name": "label",
      "type": 7
    },
    {
      "name": "style",
      "type": 2
    },
    {
      "name": "name",
      "type": 7
    }
  ],
  "rows": [
    {
      "$id": 1,
      "label": "bf11700100_0010",
      "style": 82,
      "name": "Hmmm.\nSurprisingly diligent."
    },
    {
      "$id": 2,
      "label": "bf11700100_0020",
      "style": 82,
      "name": "What is it?"
    },
    {
      "$id": 3,
      "label": "bf11700100_0030",
      "style": 82,
      "name": "Nothing, just had some time to kill."
    },
    {
      "$id": 4,
      "label": "bf11700100_0040",
      "style": 82,
      "name": "I don't think I'm the right person\nfor killing time with."
    },
    {
      "$id": 5,
      "label": "bf11700100_0050",
      "style": 82,
      "name": "Kagutsuchi's the same.\nAre there a lot of Blades who keep journals?"
    },
    {
      "$id": 6,
      "label": "bf11700100_0060",
      "style": 82,
      "name": "I don't know."
    },
    {
      "$id": 7,
      "label": "bf11700100_0065",
      "style": 82,
      "name": "Others are others, I am me."
    },
    {
      "$id": 8,
      "label": "bf11700100_0070",
      "style": 82,
      "name": "You go back to your Core when your Driver dies, right?"
    },
    {
      "$id": 9,
      "label": "bf11700100_0075",
      "style": 82,
      "name": "Seems pointless to me."
    },
    {
      "$id": 10,
      "label": "bf11700100_0080",
      "style": 82,
      "name": "It's not unnatural to want to know who you were,\nthe next time you awaken."
    },
    {
      "$id": 11,
      "label": "bf11700100_0090",
      "style": 82,
      "name": "There's no guarantee it'll still be there, right?"
    },
    {
      "$id": 12,
      "label": "bf11700100_0100",
      "style": 82,
      "name": "Even so..."
    },
    {
      "$id": 13,
      "label": "bf11700100_0105",
      "style": 82,
      "name": "Even if it's uncertain,\nwe still want something to cling to."
    },
    {
      "$id": 14,
      "label": "bf11700100_0110",
      "style": 82,
      "name": "That's just how we are."
    },
    {
      "$id": 15,
      "label": "bf11700100_0120",
      "style": 82,
      "name": "What for?"
    },
    {
      "$id": 16,
      "label": "bf11700100_0130",
      "style": 82,
      "name": "For the bond with the Driver we believed in."
    },
    {
      "$id": 17,
      "label": "bf11700100_0140",
      "style": 82,
      "name": "The bond...?"
    },
    {
      "$id": 18,
      "label": "bf11700100_0150",
      "style": 82,
      "name": "I don't expect you to understand right now."
    },
    {
      "$id": 19,
      "label": "bf11700100_0160",
      "style": 82,
      "name": "What a nasty thing to say."
    },
    {
      "$id": 20,
      "label": "bf11700100_0165",
      "style": 82,
      "name": "You make it sound like I don't have a heart."
    },
    {
      "$id": 21,
      "label": "bf11700100_0170",
      "style": 82,
      "name": "[ML:undisp ]heh."
    },
    {
      "$id": 22,
      "label": "bf11700100_0180",
      "style": 82,
      "name": "What...?"
    },
    {
      "$id": 23,
      "label": "bf11700100_0190",
      "style": 82,
      "name": "What I meant was,"
    },
    {
      "$id": 24,
      "label": "bf11700100_0200",
      "style": 82,
      "name": "maybe the bond you're supposed to make isn't here."
    },
    {
      "$id": 25,
      "label": "bf11700100_0210",
      "style": 82,
      "name": "But Adel is my Driver."
    },
    {
      "$id": 26,
      "label": "bf11700100_0220",
      "style": 82,
      "name": "That's true, but something feels different."
    },
    {
      "$id": 27,
      "label": "bf11700100_0230",
      "style": 82,
      "name": "Huh?"
    },
    {
      "$id": 28,
      "label": "bf11700100_0240",
      "style": 82,
      "name": "Your bond lies in the future, not the present."
    },
    {
      "$id": 29,
      "label": "bf11700100_0250",
      "style": 82,
      "name": "Just a hunch."
    },
    {
      "$id": 30,
      "label": "bf11700100_0255",
      "style": 82,
      "name": "A hunch. From just a regular Blade."
    },
    {
      "$id": 31,
      "label": "bf11700100_0260",
      "style": 82,
      "name": "Doesn't sound too reliable."
    },
    {
      "$id": 32,
      "label": "bf11700100_0270",
      "style": 82,
      "name": "Anyway, sorry about before."
    },
    {
      "$id": 33,
      "label": "bf11700100_0280",
      "style": 82,
      "name": "For what?"
    },
    {
      "$id": 34,
      "label": "bf11700100_0290",
      "style": 82,
      "name": "I was surprised."
    },
    {
      "$id": 35,
      "label": "bf11700100_0300",
      "style": 82,
      "name": "Both you and that kid are so awkward."
    },
    {
      "$id": 36,
      "label": "bf11700100_0305",
      "style": 82,
      "name": "I couldn't just stand by and watch."
    },
    {
      "$id": 37,
      "label": "bf11700100_0310",
      "style": 82,
      "name": "[ML:undisp ]Huh."
    },
    {
      "$id": 38,
      "label": "bf11700100_0320",
      "style": 82,
      "name": "That's rich, coming from you."
    }
  ]
}