{
  "schema": [
    {
      "name": "label",
      "type": 7
    },
    {
      "name": "style",
      "type": 2
    },
    {
      "name": "name",
      "type": 7
    }
  ],
  "rows": [
    {
      "$id": 1,
      "label": "bf04380100_0010",
      "style": 82,
      "name": "Hah! Justice always prevail!"
    },
    {
      "$id": 2,
      "label": "bf04380100_0020",
      "style": 82,
      "name": "Masterpon, that enough gloating now."
    },
    {
      "$id": 3,
      "label": "bf04380100_0030",
      "style": 82,
      "name": "Now maybe you too won't be\nused for bad things any more."
    },
    {
      "$id": 4,
      "label": "bf04380100_0040",
      "style": 82,
      "name": "Ahhhh!"
    },
    {
      "$id": 5,
      "label": "bf04380100_0050",
      "style": 82,
      "name": "Bahn's vanished again!"
    },
    {
      "$id": 6,
      "label": "bf04380100_0060",
      "style": 82,
      "name": "Over there, my lady!"
    },
    {
      "$id": 7,
      "label": "bf04380100_0070",
      "style": 82,
      "name": "Hold it!"
    }
  ]
}