{
  "schema": [
    {
      "name": "label",
      "type": 7
    },
    {
      "name": "style",
      "type": 2
    },
    {
      "name": "name",
      "type": 7
    }
  ],
  "rows": [
    {
      "$id": 1,
      "label": "qst200913_msg001",
      "style": 84,
      "name": "Ah, there he is! Kupon-san!"
    },
    {
      "$id": 2,
      "label": "qst200913_msg002",
      "style": 84,
      "name": "Oh no! He's being attacked\nby the Tirkin tribe! We\nhave to help him quickly!"
    },
    {
      "$id": 3,
      "label": "qst200913_msg003",
      "style": 84,
      "name": "Go away, mo! Kupon is\nnot your food, mo!"
    },
    {
      "$id": 4,
      "label": "qst200913_msg004",
      "style": 84,
      "name": "Gyaaaaaah!!"
    },
    {
      "$id": 5,
      "label": "qst200913_msg005",
      "style": 84,
      "name": "Kasane?! This is bad, mo!\nDon't you come here, mo!"
    },
    {
      "$id": 6,
      "label": "qst200913_msg006",
      "style": 84,
      "name": "It's alright now! I'll save you!"
    },
    {
      "$id": 7,
      "label": "qst200913_msg007",
      "style": 84,
      "name": "No, mo! Don't come any closer, mo!!"
    },
    {
      "$id": 8,
      "label": "qst200913_msg008",
      "style": 84,
      "name": "...Ah, this is bad, mo."
    },
    {
      "$id": 9,
      "label": "qst200913_msg009",
      "style": 84,
      "name": "Are you alright?"
    },
    {
      "$id": 10,
      "label": "qst200913_msg010",
      "style": 84,
      "name": "...It seems we have to help him again."
    }
  ]
}