{
  "schema": [
    {
      "name": "label",
      "type": 7
    },
    {
      "name": "style",
      "type": 2
    },
    {
      "name": "name",
      "type": 7
    }
  ],
  "rows": [
    {
      "$id": 1,
      "label": "campfev11_410_100_msg0001",
      "style": 84,
      "name": "Maybe I haven't trained enough yet..."
    },
    {
      "$id": 2,
      "label": "campfev11_410_100_msg0002",
      "style": 84,
      "name": "How about you train with Kasumi\nthis time?"
    },
    {
      "$id": 3,
      "label": "campfev11_410_100_msg0003",
      "style": 84,
      "name": "I'm happy to help!"
    },
    {
      "$id": 4,
      "label": "campfev11_410_100_msg0004",
      "style": 84,
      "name": "Sure, training's great. But I think the\nreal problem here is strategy."
    },
    {
      "$id": 5,
      "label": "campfev11_410_100_msg0005",
      "style": 84,
      "name": "Maybe you have a point."
    },
    {
      "$id": 6,
      "label": "campfev11_410_100_msg0006",
      "style": 84,
      "name": "Since Hugo and Wadatsumi are back, why\ndon't we all put our heads together and\nsee if we can refresh our tactics?"
    },
    {
      "$id": 7,
      "label": "campfev11_410_100_msg0007",
      "style": 84,
      "name": "Wadatsumi and I are at your care\nAdel! Aren't we Wadatsumi!"
    },
    {
      "$id": 8,
      "label": "campfev11_410_100_msg0008",
      "style": 84,
      "name": "Indeed! We will do all we can to\nlock step with you, Prince!"
    },
    {
      "$id": 9,
      "label": "campfev11_410_100_msg0009",
      "style": 84,
      "name": "It's looking good for training."
    },
    {
      "$id": 10,
      "label": "campfev11_410_100_msg0010",
      "style": 84,
      "name": "When we've worked over our tactics,\nlet's set out on Olnard's Trail."
    }
  ]
}