{
  "schema": [
    {
      "name": "label",
      "type": 7
    },
    {
      "name": "style",
      "type": 2
    },
    {
      "name": "name",
      "type": 7
    }
  ],
  "rows": [
    {
      "$id": 1,
      "label": "tlk41400021_01_msg0001",
      "style": 84,
      "name": "When you think of Gula, you think of its\nlush, green land! Furniture made from\nGulan wood makes the perfect souvenir!"
    },
    {
      "$id": 2,
      "label": "tlk41400021_01_msg0002",
      "style": 84,
      "name": "It's wonderful, isn't it! This city\nof Torigoth has an even richer supply\nof trees than other Gulan cities."
    },
    {
      "$id": 3,
      "label": "tlk41400021_01_msg0003",
      "style": 84,
      "name": "The quality of our specialty products\nis different from other Gulan cities.\nAfter all, it's handmade! Handmade!"
    },
    {
      "$id": 4,
      "label": "tlk41400021_01_msg0004",
      "style": 84,
      "name": "Once you pick it up, you're\nsure to be captivated!"
    }
  ]
}